Synchronous_FIFO/Synchronous_FIFO.v

module Sync_FIFO #( 
    parameter DEPTH = 8, 
    parameter WIDTH = 8
) (
    input wire clk, 
    input wire rst, 
    input wire wr_en, 
    input wire rd_en,
    input wire [WIDTH-1:0] data_in,

    output reg [WIDTH-1:0] data_out,
    output wire full, 
    output wire empty
);

    // Pointer width: extra MSB for wrap detection
    localparam PTR_WIDTH = $clog2(DEPTH);

    reg [PTR_WIDTH:0] w_ptr, r_ptr;

    // Memory
    reg [WIDTH-1:0] Fifo [0:DEPTH-1];

    // WRITE LOGIC

    always @(posedge clk) begin
        if (rst) begin
            w_ptr <= 0;
        end 
        else if (wr_en && (!full || rd_en)) begin
            // allow write if read also happening (prevents stall at full)
            Fifo[w_ptr[PTR_WIDTH-1:0]] <= data_in;
            w_ptr <= w_ptr + 1'b1;
        end
    end

    // READ LOGIC

    always @(posedge clk) begin
        if (rst) begin
            r_ptr   <= 0;
            data_out <= 0;
        end 
        else if (rd_en && !empty) begin
            data_out <= Fifo[r_ptr[PTR_WIDTH-1:0]];
            r_ptr <= r_ptr + 1'b1;
        end
    end

    initial begin
    if (DEPTH & (DEPTH - 1))
        $error("DEPTH must be power of 2");
    end

    // STATUS FLAGS


    // EMPTY: pointers equal
    assign empty = (w_ptr == r_ptr);

    // FULL: MSB different, rest same
    assign full = (w_ptr[PTR_WIDTH] != r_ptr[PTR_WIDTH]) && (w_ptr[PTR_WIDTH-1:0] == r_ptr[PTR_WIDTH-1:0]);

endmodule

Synchronous_FIFO/test.v

`include "Synchronous_FIFO.v"

`timescale 1ns/1ps

module tb_Sync_FIFO;

    parameter DEPTH = 8;
    parameter WIDTH = 8;

    reg clk, rst;
    reg wr_en, rd_en;
    reg [WIDTH-1:0] data_in;

    wire [WIDTH-1:0] data_out;
    wire full, empty;

    // DUT
    Sync_FIFO #(DEPTH, WIDTH) dut (
        .clk(clk),
        .rst(rst),
        .wr_en(wr_en),
        .rd_en(rd_en),
        .data_in(data_in),
        .data_out(data_out),
        .full(full),
        .empty(empty)
    );

    // Clock
    always #5 clk = ~clk;

    // Reference model
    reg [WIDTH-1:0] ref_mem [0:DEPTH-1];
    integer w_ref = 0, r_ref = 0;

    // -------------------------------
    // WRITE TASK (FINAL)
    // -------------------------------
    task write(input [WIDTH-1:0] data);
        reg do_write;
    begin
        @(negedge clk);

        do_write = !full;   // capture condition BEFORE clock

        wr_en = 1;
        rd_en = 0;
        data_in = data;

        @(posedge clk);     // write happens

        @(negedge clk);
        wr_en = 0;

        if (do_write) begin
            ref_mem[w_ref] = data;
            w_ref = (w_ref + 1) % DEPTH;
        end
    end
    endtask

    // -------------------------------
    // READ TASK (FINAL)
    // -------------------------------
    task read;
        reg do_read;
    begin
        @(negedge clk);

        do_read = !empty;   // capture condition BEFORE clock

        rd_en = 1;
        wr_en = 0;

        @(posedge clk);     // read happens

        @(negedge clk);
        rd_en = 0;

        if (do_read) begin
            if (data_out !== ref_mem[r_ref]) begin
                $display("ERROR: Expected %0d, Got %0d at time %0t",
                         ref_mem[r_ref], data_out, $time);
            end else begin
                $display("READ OK: %0d at time %0t", data_out, $time);
            end

            r_ref = (r_ref + 1) % DEPTH;
        end else begin
            $display("READ BLOCKED (EMPTY) at time %0t", $time);
        end
    end
    endtask

    // -------------------------------
    // INITIAL BLOCK
    // -------------------------------
    initial begin
        // waveform dump
        $dumpfile("fifo.vcd");
        $dumpvars(0, tb_Sync_FIFO);

        clk = 0;
        rst = 1;
        wr_en = 0;
        rd_en = 0;
        data_in = 0;

        #20 rst = 0;

        // TEST 1: Write
        $display("\nTEST 1: Writing data");
        write(10);
        write(20);
        write(30);

        // TEST 2: Read
        $display("\nTEST 2: Reading data");
        read();
        read();
        read();

        // TEST 3: Fill FIFO
        $display("\nTEST 3: Fill FIFO");
        repeat (DEPTH) write($random);

        // TEST 4: Overflow
        $display("\nTEST 4: Overflow attempt");
        write(99);

        // TEST 5: Empty FIFO
        $display("\nTEST 5: Empty FIFO");
        repeat (DEPTH) read();

        // TEST 6: Underflow
        $display("\nTEST 6: Underflow attempt");
        read();

        // TEST 7: Simultaneous Read/Write
        $display("\nTEST 7: Simultaneous Read/Write");

        write(55);
        write(66);

        @(negedge clk);
        wr_en = 1;
        rd_en = 1;
        data_in = 77;

        @(posedge clk);

        @(negedge clk);
        wr_en = 0;
        rd_en = 0;

        #50;
        $display("\nSimulation Finished");
        $finish;
    end

endmodule

Synchronous_FIFO/fifo.vcd
$date
	Mon Apr  6 10:10:50 2026
$end
$version
	Icarus Verilog
$end
$timescale
	1ps
$end
$scope module tb_Sync_FIFO $end
$var wire 1 ! full $end
$var wire 1 " empty $end
$var wire 8 # data_out [7:0] $end
$var parameter 32 $ DEPTH $end
$var parameter 32 % WIDTH $end
$var reg 1 & clk $end
$var reg 8 ' data_in [7:0] $end
$var reg 1 ( rd_en $end
$var reg 1 ) rst $end
$var reg 1 * wr_en $end
$var integer 32 + r_ref [31:0] $end
$var integer 32 , w_ref [31:0] $end
$scope module dut $end
$var wire 1 & clk $end
$var wire 8 - data_in [7:0] $end
$var wire 1 ! full $end
$var wire 1 ( rd_en $end
$var wire 1 ) rst $end
$var wire 1 * wr_en $end
$var wire 1 " empty $end
$var parameter 32 . DEPTH $end
$var parameter 32 / PTR_WIDTH $end
$var parameter 32 0 WIDTH $end
$var reg 8 1 data_out [7:0] $end
$var reg 4 2 r_ptr [3:0] $end
$var reg 4 3 w_ptr [3:0] $end
$upscope $end
$scope task read $end
$var reg 1 4 do_read $end
$upscope $end
$scope task write $end
$var reg 8 5 data [7:0] $end
$var reg 1 6 do_write $end
$upscope $end
$upscope $end
$enddefinitions $end
$comment Show the parameter values. $end
$dumpall
b1000 0
b11 /
b1000 .
b1000 %
b1000 $
$end
#0
$dumpvars
x6
bx 5
x4
bx 3
bx 2
bx 1
b0 -
b0 ,
b0 +
0*
1)
0(
b0 '
0&
bx #
x"
x!
$end
#5000
0!
1"
b0 3
b0 #
b0 1
b0 2
1&
#10000
0&
#15000
1&
#20000
b1010 '
b1010 -
1*
16
0&
b1010 5
0)
#25000
0"
b1 3
1&
#30000
b10100 5
b1 ,
0*
0&
#35000
1&
#40000
b10100 '
b10100 -
1*
0&
#45000
b10 3
1&
#50000
b11110 5
b10 ,
0*
0&
#55000
1&
#60000
b11110 '
b11110 -
1*
0&
#65000
b11 3
1&
#70000
b11 ,
0*
0&
#75000
1&
#80000
1(
14
0&
#85000
b1 2
b1010 #
b1010 1
1&
#90000
b1 +
0(
0&
#95000
1&
#100000
1(
0&
#105000
b10 2
b10100 #
b10100 1
1&
#110000
b10 +
0(
0&
#115000
1&
#120000
1(
0&
#125000
1"
b11 2
b11110 #
b11110 1
1&
#130000
b100100 5
b11 +
0(
0&
#135000
1&
#140000
b100100 '
b100100 -
1*
0&
#145000
0"
b100 3
1&
#150000
b10000001 5
b100 ,
0*
0&
#155000
1&
#160000
b10000001 '
b10000001 -
1*
0&
#165000
b101 3
1&
#170000
b1001 5
b101 ,
0*
0&
#175000
1&
#180000
b1001 '
b1001 -
1*
0&
#185000
b110 3
1&
#190000
b1100011 5
b110 ,
0*
0&
#195000
1&
#200000
b1100011 '
b1100011 -
1*
0&
#205000
b111 3
1&
#210000
b1101 5
b111 ,
0*
0&
#215000
1&
#220000
b1101 '
b1101 -
1*
0&
#225000
b1000 3
1&
#230000
b10001101 5
b0 ,
0*
0&
#235000
1&
#240000
b10001101 '
b10001101 -
1*
0&
#245000
b1001 3
1&
#250000
b1100101 5
b1 ,
0*
0&
#255000
1&
#260000
b1100101 '
b1100101 -
1*
0&
#265000
b1010 3
1&
#270000
b10010 5
b10 ,
0*
0&
#275000
1&
#280000
b10010 '
b10010 -
1*
0&
#285000
1!
b1011 3
1&
#290000
b1100011 5
b11 ,
0*
0&
#295000
1&
#300000
b1100011 '
b1100011 -
1*
06
0&
#305000
1&
#310000
0*
0&
#315000
1&
#320000
1(
0&
#325000
0!
b100 2
b100100 #
b100100 1
1&
#330000
b100 +
0(
0&
#335000
1&
#340000
1(
0&
#345000
b101 2
b10000001 #
b10000001 1
1&
#350000
b101 +
0(
0&
#355000
1&
#360000
1(
0&
#365000
b110 2
b1001 #
b1001 1
1&
#370000
b110 +
0(
0&
#375000
1&
#380000
1(
0&
#385000
b111 2
b1100011 #
b1100011 1
1&
#390000
b111 +
0(
0&
#395000
1&
#400000
1(
0&
#405000
b1000 2
b1101 #
b1101 1
1&
#410000
b0 +
0(
0&
#415000
1&
#420000
1(
0&
#425000
b1001 2
b10001101 #
b10001101 1
1&
#430000
b1 +
0(
0&
#435000
1&
#440000
1(
0&
#445000
b1010 2
b1100101 #
b1100101 1
1&
#450000
b10 +
0(
0&
#455000
1&
#460000
1(
0&
#465000
1"
b1011 2
b10010 #
b10010 1
1&
#470000
b11 +
0(
0&
#475000
1&
#480000
1(
04
0&
#485000
1&
#490000
b110111 5
0(
0&
#495000
1&
#500000
b110111 '
b110111 -
1*
16
0&
#505000
0"
b1100 3
1&
#510000
b1000010 5
b100 ,
0*
0&
#515000
1&
#520000
b1000010 '
b1000010 -
1*
0&
#525000
b1101 3
1&
#530000
b101 ,
0*
0&
#535000
1&
#540000
b1001101 '
b1001101 -
1(
1*
0&
#545000
b1110 3
b1100 2
b110111 #
b110111 1
1&
#550000
0(
0*
0&
